README.txt
setup.cfg
setup.py
ulint/__init__.py
ulint/ulint
ulint.egg-info/PKG-INFO
ulint.egg-info/SOURCES.txt
ulint.egg-info/dependency_links.txt
ulint.egg-info/requires.txt
ulint.egg-info/top_level.txt