Metadata-Version: 1.1
Name: ulint
Version: 0.1.1
Summary: Utility and library to easily run linters on your source code handling virtually any language
Home-page: http://packages.python.org/ulint
Author: Thibault Saunier
Author-email: tsaunier@gnome.org
License: LGPL
Keywords: lint tool code quality
Platform: UNKNOWN
Classifier: Topic :: Utilities
Classifier: License :: OSI Approved :: GNU Lesser General Public License v2 (LGPLv2) 
